MANIFEST.in
Makefile
README.rst
setup.py
django_separatedvaluesfield.egg-info/PKG-INFO
django_separatedvaluesfield.egg-info/SOURCES.txt
django_separatedvaluesfield.egg-info/dependency_links.txt
django_separatedvaluesfield.egg-info/not-zip-safe
django_separatedvaluesfield.egg-info/pbr.json
django_separatedvaluesfield.egg-info/top_level.txt
separatedvaluesfield/__init__.py
separatedvaluesfield/models.py
separatedvaluesfield/tests/__init__.py
separatedvaluesfield/tests/models.py
separatedvaluesfield/tests/settings.py
separatedvaluesfield/tests/tests.py